{
  "paroquia": [
    {
      "dioceseId": "12",
      "organismoId": "2150,
	  "codigo":1,
      "razao_socials": "PAROQUIA IMACULADA CONCEIÇAO - SARUTAIÁ"
    },
    {
      "dioceseId": "12",
      "organismoId": "2151",
	  "codigo":2,
      "razao_social": "PAROQUIA ESPIRITO SANTO - ESP. STO TURVO"
    },
    {
      "dioceseId": "12",
      "organismoId": "2152",
	  "codigo":3,
      "razao_social": "PAROQUIA DIVINDO ESPIRITO SANTO - UBIRAJARA"
    },
    {
      "dioceseId": "12",
      "organismoId": "2153",
	  "codigo":4,
      "razao_social": "PAROQUIA N SRA AP. DO VAGAO QUEIMADO - OURINHOS"
    },
    {
      "dioceseId": "12",
      "organismoId": "2154",
	  "codigo":5,
      "razao_social": "PAROQUIA N SRA APARECIDA - CHAVANTES"
    }
  ]
}